{
  "user_id": "30a6392e-cb67-46bc-a21d-f62ea44d0d67",
  "user_number": 489,
  "primary_photo": {
    "original_url": "https://apps.parthaisolutions.com/ai-matchmaking/api/matrimony/static/profile_pics/30a6392e-cb67-46bc-a21d-f62ea44d0d67/4c7b6775-d19d-4921-8aa0-bc4955e137d9.jpg",
    "cropped_path": "user489_primary.jpg",
    "embedding_path": "user489_primary_embedding.npy",
    "face_detected": true,
    "face_info": {
      "bbox": "[215.96782 118.04382 369.59723 296.36237]",
      "det_score": "0.8955592",
      "age": 33,
      "gender": "1"
    }
  },
  "additional_photos": [
    {
      "original_url": "https://apps.parthaisolutions.com/ai-matchmaking/api/matrimony/static/profile_pics/30a6392e-cb67-46bc-a21d-f62ea44d0d67/5aaf7825-ad0d-48aa-be2d-538e4f0662c6.jpg",
      "cropped_path": "user489_additional_1.jpg",
      "embedding_path": "user489_additional_1_embedding.npy",
      "face_detected": true,
      "face_info": {
        "bbox": "[240.76558 187.32648 548.3637  519.63184]",
        "det_score": "0.8332329",
        "age": 42,
        "gender": "1"
      }
    },
    {
      "original_url": "https://apps.parthaisolutions.com/ai-matchmaking/api/matrimony/static/profile_pics/30a6392e-cb67-46bc-a21d-f62ea44d0d67/9d288c9a-9283-4cd2-b969-8cbf7e969950.jpg",
      "cropped_path": "user489_additional_2.jpg",
      "embedding_path": "user489_additional_2_embedding.npy",
      "face_detected": true,
      "face_info": {
        "bbox": "[155.99931 222.23477 433.0982  561.76135]",
        "det_score": "0.72888887",
        "age": 43,
        "gender": "1"
      }
    }
  ],
  "cropped_images": [
    "user489_primary.jpg",
    "user489_additional_1.jpg",
    "user489_additional_2.jpg"
  ]
}