{
  "user_id": "d9061800-b1f7-46b6-b6ad-c69fca3f0588",
  "user_number": 2106,
  "primary_photo": {
    "original_url": "https://apps.parthaisolutions.com/ai-matchmaking/api/matrimony/static/profile_pics/d9061800-b1f7-46b6-b6ad-c69fca3f0588/00c8b266-505f-4510-92e7-a07fd327c655.jpg",
    "cropped_path": "user2106_primary.jpg",
    "embedding_path": "user2106_primary_embedding.npy",
    "face_detected": true,
    "face_info": {
      "bbox": "[336.592   287.95792 394.70947 361.93442]",
      "det_score": "0.8815192",
      "age": 30,
      "gender": "1"
    }
  },
  "additional_photos": [
    {
      "original_url": "https://apps.parthaisolutions.com/ai-matchmaking/api/matrimony/static/profile_pics/d9061800-b1f7-46b6-b6ad-c69fca3f0588/4076d448-8366-4062-bbfe-3e82e2782b90.jpg",
      "cropped_path": "user2106_additional_1.jpg",
      "embedding_path": "user2106_additional_1_embedding.npy",
      "face_detected": true,
      "face_info": {
        "bbox": "[274.10663 226.8677  435.69443 424.61572]",
        "det_score": "0.90151274",
        "age": 38,
        "gender": "1"
      }
    }
  ],
  "cropped_images": [
    "user2106_primary.jpg",
    "user2106_additional_1.jpg"
  ]
}