{
  "user_id": "3c589e15-a853-454e-b86d-be0e4d73ba5e",
  "user_number": 616,
  "primary_photo": {
    "original_url": "https://apps.parthaisolutions.com/ai-matchmaking/api/matrimony/static/profile_pics/3c589e15-a853-454e-b86d-be0e4d73ba5e/665c293c-2e83-4486-a0bb-35b4bb4d93f3.jpg",
    "cropped_path": "user616_primary.jpg",
    "embedding_path": "user616_primary_embedding.npy",
    "face_detected": true,
    "face_info": {
      "bbox": "[541.6586  252.79517 633.15515 364.75732]",
      "det_score": "0.89966786",
      "age": 32,
      "gender": "1"
    }
  },
  "additional_photos": [
    {
      "original_url": "https://apps.parthaisolutions.com/ai-matchmaking/api/matrimony/static/profile_pics/3c589e15-a853-454e-b86d-be0e4d73ba5e/38732339-593a-4284-a22b-a0d012ce97e9.jpg",
      "cropped_path": "user616_additional_1.jpg",
      "embedding_path": "user616_additional_1_embedding.npy",
      "face_detected": true,
      "face_info": {
        "bbox": "[464.38995 220.16138 594.72314 392.0112 ]",
        "det_score": "0.81234187",
        "age": 34,
        "gender": "1"
      }
    },
    {
      "original_url": "https://apps.parthaisolutions.com/ai-matchmaking/api/matrimony/static/profile_pics/3c589e15-a853-454e-b86d-be0e4d73ba5e/1104c49e-63fc-4a6a-8592-4573b7f41fa3.jpg",
      "cropped_path": "user616_additional_2.jpg",
      "embedding_path": "user616_additional_2_embedding.npy",
      "face_detected": true,
      "face_info": {
        "bbox": "[303.65656 285.89377 430.71307 437.55353]",
        "det_score": "0.91032267",
        "age": 43,
        "gender": "1"
      }
    },
    {
      "original_url": "https://apps.parthaisolutions.com/ai-matchmaking/api/matrimony/static/profile_pics/3c589e15-a853-454e-b86d-be0e4d73ba5e/376ba20c-9506-4078-b863-ed49b0ab482c.jpg",
      "cropped_path": "user616_additional_3.jpg",
      "embedding_path": "user616_additional_3_embedding.npy",
      "face_detected": true,
      "face_info": {
        "bbox": "[425.39767 129.2307  564.8745  298.83545]",
        "det_score": "0.8733255",
        "age": 44,
        "gender": "1"
      }
    }
  ],
  "cropped_images": [
    "user616_primary.jpg",
    "user616_additional_1.jpg",
    "user616_additional_2.jpg",
    "user616_additional_3.jpg"
  ]
}