{
  "user_id": "5a12b8fc-781f-4029-9e5c-b132c251b6a1",
  "user_number": 902,
  "primary_photo": {
    "original_url": "https://apps.parthaisolutions.com/ai-matchmaking/api/matrimony/static/profile_pics/5a12b8fc-781f-4029-9e5c-b132c251b6a1/6edcf1aa-881b-42ae-a36d-a6c20597ce22.jpeg",
    "cropped_path": "user902_primary.jpg",
    "embedding_path": "user902_primary_embedding.npy",
    "face_detected": true,
    "face_info": {
      "bbox": "[267.10724 460.2369  311.68674 514.348  ]",
      "det_score": "0.7570604",
      "age": 36,
      "gender": "1"
    }
  },
  "additional_photos": [
    {
      "original_url": "https://apps.parthaisolutions.com/ai-matchmaking/api/matrimony/static/profile_pics/5a12b8fc-781f-4029-9e5c-b132c251b6a1/885c44df-c61e-43dd-ac1b-c531337752f3.jpeg",
      "cropped_path": "user902_additional_1.jpg",
      "embedding_path": "user902_additional_1_embedding.npy",
      "face_detected": true,
      "face_info": {
        "bbox": "[291.77905 131.37717 374.5665  249.26018]",
        "det_score": "0.7748963",
        "age": 30,
        "gender": "1"
      }
    }
  ],
  "cropped_images": [
    "user902_primary.jpg",
    "user902_additional_1.jpg"
  ]
}