{
  "user_id": "59501ad9-0b34-4327-be50-8f3f2d9e9384",
  "user_number": 895,
  "primary_photo": {
    "original_url": "https://apps.parthaisolutions.com/ai-matchmaking/api/matrimony/static/profile_pics/59501ad9-0b34-4327-be50-8f3f2d9e9384/e0c0c4a0-5554-4e9d-b842-9fd109f30f87.jpg",
    "cropped_path": "user895_primary.jpg",
    "embedding_path": "user895_primary_embedding.npy",
    "face_detected": true,
    "face_info": {
      "bbox": "[285.37103  78.75071 504.20572 353.20844]",
      "det_score": "0.91574967",
      "age": 46,
      "gender": "1"
    }
  },
  "additional_photos": [
    {
      "original_url": "https://apps.parthaisolutions.com/ai-matchmaking/api/matrimony/static/profile_pics/59501ad9-0b34-4327-be50-8f3f2d9e9384/81beb388-0f83-4ca5-a322-782f69f174f3.jpg",
      "cropped_path": "user895_additional_1.jpg",
      "embedding_path": "user895_additional_1_embedding.npy",
      "face_detected": true,
      "face_info": {
        "bbox": "[194.22882 215.5115  460.72662 562.31213]",
        "det_score": "0.80655116",
        "age": 56,
        "gender": "1"
      }
    }
  ],
  "cropped_images": [
    "user895_primary.jpg",
    "user895_additional_1.jpg"
  ]
}