{
  "user_id": "e94e65ea-caeb-41ca-8c9b-8761530d38ac",
  "user_number": 2265,
  "primary_photo": {
    "original_url": "https://apps.parthaisolutions.com/ai-matchmaking/api/matrimony/static/profile_pics/e94e65ea-caeb-41ca-8c9b-8761530d38ac/20c6b95a-f429-48a5-9c28-46fd57922434.jpg",
    "cropped_path": "user2265_primary.jpg",
    "embedding_path": "user2265_primary_embedding.npy",
    "face_detected": true,
    "face_info": {
      "bbox": "[361.66113 296.66382 439.26602 388.9334 ]",
      "det_score": "0.88866377",
      "age": 29,
      "gender": "1"
    }
  },
  "additional_photos": [
    {
      "original_url": "https://apps.parthaisolutions.com/ai-matchmaking/api/matrimony/static/profile_pics/e94e65ea-caeb-41ca-8c9b-8761530d38ac/f801f83c-b77d-4252-99d3-6b0306f91c90.jpg",
      "cropped_path": "user2265_additional_1.jpg",
      "embedding_path": "user2265_additional_1_embedding.npy",
      "face_detected": true,
      "face_info": {
        "bbox": "[356.22104 163.08447 417.2972  234.62556]",
        "det_score": "0.87938833",
        "age": 26,
        "gender": "1"
      }
    },
    {
      "original_url": "https://apps.parthaisolutions.com/ai-matchmaking/api/matrimony/static/profile_pics/e94e65ea-caeb-41ca-8c9b-8761530d38ac/3d2035c4-7a7b-42df-9ab2-1092c93389f7.jpg",
      "cropped_path": "user2265_additional_2.jpg",
      "embedding_path": "user2265_additional_2_embedding.npy",
      "face_detected": true,
      "face_info": {
        "bbox": "[342.14038 390.1747  540.6289  653.37836]",
        "det_score": "0.9157914",
        "age": 28,
        "gender": "1"
      }
    },
    {
      "original_url": "https://apps.parthaisolutions.com/ai-matchmaking/api/matrimony/static/profile_pics/e94e65ea-caeb-41ca-8c9b-8761530d38ac/10d72208-1bd5-4c7f-b44a-937622811978.jpg",
      "cropped_path": "user2265_additional_3.jpg",
      "embedding_path": "user2265_additional_3_embedding.npy",
      "face_detected": true,
      "face_info": {
        "bbox": "[372.84927 306.20865 426.6107  368.37894]",
        "det_score": "0.87394947",
        "age": 36,
        "gender": "1"
      }
    },
    {
      "original_url": "https://apps.parthaisolutions.com/ai-matchmaking/api/matrimony/static/profile_pics/e94e65ea-caeb-41ca-8c9b-8761530d38ac/5d2aef50-3d90-45dd-b303-3ea7b5c28bfb.jpg",
      "cropped_path": "user2265_additional_4.jpg",
      "embedding_path": "user2265_additional_4_embedding.npy",
      "face_detected": true,
      "face_info": {
        "bbox": "[424.72446 273.5871  492.84116 354.83923]",
        "det_score": "0.86511165",
        "age": 35,
        "gender": "1"
      }
    }
  ],
  "cropped_images": [
    "user2265_primary.jpg",
    "user2265_additional_1.jpg",
    "user2265_additional_2.jpg",
    "user2265_additional_3.jpg",
    "user2265_additional_4.jpg"
  ]
}