{
  "user_id": "bea9d904-1fe0-43bc-b267-b18f5d52cbb1",
  "user_number": 1838,
  "primary_photo": {
    "original_url": "https://apps.parthaisolutions.com/ai-matchmaking/api/matrimony/static/profile_pics/bea9d904-1fe0-43bc-b267-b18f5d52cbb1/b0e7ca24-9777-4601-8550-c844a00db21e.jpg",
    "cropped_path": "user1838_primary.jpg",
    "embedding_path": "user1838_primary_embedding.npy",
    "face_detected": true,
    "face_info": {
      "bbox": "[326.96277 182.97191 407.70624 276.70782]",
      "det_score": "0.8971608",
      "age": 35,
      "gender": "1"
    }
  },
  "additional_photos": [
    {
      "original_url": "https://apps.parthaisolutions.com/ai-matchmaking/api/matrimony/static/profile_pics/bea9d904-1fe0-43bc-b267-b18f5d52cbb1/a75522a8-8e79-4d59-a06f-8c154159bfd8.jpg",
      "cropped_path": "user1838_additional_1.jpg",
      "embedding_path": "user1838_additional_1_embedding.npy",
      "face_detected": true,
      "face_info": {
        "bbox": "[229.5568  175.99384 298.06732 260.58975]",
        "det_score": "0.882541",
        "age": 35,
        "gender": "1"
      }
    }
  ],
  "cropped_images": [
    "user1838_primary.jpg",
    "user1838_additional_1.jpg"
  ]
}