{
  "user_id": "b584f455-6235-45ba-b8fa-5fb3bbe353fb",
  "user_number": 1751,
  "primary_photo": {
    "original_url": "https://apps.parthaisolutions.com/ai-matchmaking/api/matrimony/static/profile_pics/b584f455-6235-45ba-b8fa-5fb3bbe353fb/3a966048-9f72-48e6-89bd-dbdf66d53a17.png",
    "cropped_path": "user1751_primary.jpg",
    "embedding_path": "user1751_primary_embedding.npy",
    "face_detected": true,
    "face_info": {
      "bbox": "[132.93578   30.253733 178.07709   88.579506]",
      "det_score": "0.9210305",
      "age": 32,
      "gender": "1"
    }
  },
  "additional_photos": [
    {
      "original_url": "https://apps.parthaisolutions.com/ai-matchmaking/api/matrimony/static/profile_pics/b584f455-6235-45ba-b8fa-5fb3bbe353fb/0c80cdcf-5827-41f2-9971-1789afb950c2.png",
      "cropped_path": "user1751_additional_1.jpg",
      "embedding_path": "user1751_additional_1_embedding.npy",
      "face_detected": true,
      "face_info": {
        "bbox": "[145.73628   58.263355 193.0197   124.18059 ]",
        "det_score": "0.89956063",
        "age": 33,
        "gender": "1"
      }
    },
    {
      "original_url": "https://apps.parthaisolutions.com/ai-matchmaking/api/matrimony/static/profile_pics/b584f455-6235-45ba-b8fa-5fb3bbe353fb/0267c2c7-0d8b-4e53-9605-7b60d7313a44.png",
      "cropped_path": "user1751_additional_2.jpg",
      "embedding_path": "user1751_additional_2_embedding.npy",
      "face_detected": true,
      "face_info": {
        "bbox": "[160.76178 136.44041 188.6044  171.868  ]",
        "det_score": "0.86072075",
        "age": 30,
        "gender": "1"
      }
    },
    {
      "original_url": "https://apps.parthaisolutions.com/ai-matchmaking/api/matrimony/static/profile_pics/b584f455-6235-45ba-b8fa-5fb3bbe353fb/29e57939-bae8-49d3-af73-11aab359d5dd.png",
      "cropped_path": "user1751_additional_3.jpg",
      "embedding_path": "user1751_additional_3_embedding.npy",
      "face_detected": true,
      "face_info": {
        "bbox": "[108.09881   19.018204 148.57564   70.907906]",
        "det_score": "0.89115536",
        "age": 33,
        "gender": "1"
      }
    }
  ],
  "cropped_images": [
    "user1751_primary.jpg",
    "user1751_additional_1.jpg",
    "user1751_additional_2.jpg",
    "user1751_additional_3.jpg"
  ]
}