{
  "user_id": "bebca0fe-e046-44c5-bb8f-440b5f89f8cc",
  "user_number": 1839,
  "primary_photo": {
    "original_url": "https://apps.parthaisolutions.com/ai-matchmaking/api/matrimony/static/profile_pics/bebca0fe-e046-44c5-bb8f-440b5f89f8cc/fad41e32-882b-4487-8e3f-4a52dee57ec5.jpg",
    "cropped_path": "user1839_primary.jpg",
    "embedding_path": "user1839_primary_embedding.npy",
    "face_detected": true,
    "face_info": {
      "bbox": "[308.3042  246.94072 384.07968 341.6636 ]",
      "det_score": "0.8620336",
      "age": 41,
      "gender": "1"
    }
  },
  "additional_photos": [
    {
      "original_url": "https://apps.parthaisolutions.com/ai-matchmaking/api/matrimony/static/profile_pics/bebca0fe-e046-44c5-bb8f-440b5f89f8cc/1e51192a-907d-4530-b3df-4386c0de7aec.jpg",
      "cropped_path": "user1839_additional_1.jpg",
      "embedding_path": "user1839_additional_1_embedding.npy",
      "face_detected": true,
      "face_info": {
        "bbox": "[232.6217  190.94975 394.96307 378.04788]",
        "det_score": "0.894199",
        "age": 45,
        "gender": "1"
      }
    },
    {
      "original_url": "https://apps.parthaisolutions.com/ai-matchmaking/api/matrimony/static/profile_pics/bebca0fe-e046-44c5-bb8f-440b5f89f8cc/333f81ee-b6e1-4a1a-bc52-175eb2302abd.jpg",
      "cropped_path": "user1839_additional_2.jpg",
      "embedding_path": "user1839_additional_2_embedding.npy",
      "face_detected": true,
      "face_info": {
        "bbox": "[454.22552 413.2725  529.00836 495.9965 ]",
        "det_score": "0.8715799",
        "age": 38,
        "gender": "1"
      }
    }
  ],
  "cropped_images": [
    "user1839_primary.jpg",
    "user1839_additional_1.jpg",
    "user1839_additional_2.jpg"
  ]
}