{
  "user_id": "1834414e-676d-42e7-abb2-63eaf64703cf",
  "user_number": 255,
  "primary_photo": {
    "original_url": "https://apps.parthaisolutions.com/ai-matchmaking/api/matrimony/static/profile_pics/1834414e-676d-42e7-abb2-63eaf64703cf/eb2c4459-ad8a-47d5-a2d8-2ee1d1b26d98.png",
    "cropped_path": "user255_primary.jpg",
    "embedding_path": "user255_primary_embedding.npy",
    "face_detected": true,
    "face_info": {
      "bbox": "[461.60263 108.6276  553.20593 213.80688]",
      "det_score": "0.8986981",
      "age": 34,
      "gender": "1"
    }
  },
  "additional_photos": [
    {
      "original_url": "https://apps.parthaisolutions.com/ai-matchmaking/api/matrimony/static/profile_pics/1834414e-676d-42e7-abb2-63eaf64703cf/475202d2-b392-4ca6-902c-380603002e15.jpg",
      "cropped_path": "user255_additional_1.jpg",
      "embedding_path": "user255_additional_1_embedding.npy",
      "face_detected": true,
      "face_info": {
        "bbox": "[170.60864 109.1122  285.00308 244.97798]",
        "det_score": "0.86734533",
        "age": 26,
        "gender": "1"
      }
    },
    {
      "original_url": "https://apps.parthaisolutions.com/ai-matchmaking/api/matrimony/static/profile_pics/1834414e-676d-42e7-abb2-63eaf64703cf/5ed4f153-153c-4357-a427-9d9560a237a1.jpg",
      "cropped_path": "user255_additional_2.jpg",
      "embedding_path": "user255_additional_2_embedding.npy",
      "face_detected": true,
      "face_info": {
        "bbox": "[434.98193 384.55792 498.3711  464.1167 ]",
        "det_score": "0.84777355",
        "age": 32,
        "gender": "1"
      }
    },
    {
      "original_url": "https://apps.parthaisolutions.com/ai-matchmaking/api/matrimony/static/profile_pics/1834414e-676d-42e7-abb2-63eaf64703cf/77505e76-9bae-443b-ba29-00fe9a19fb2b.jpg",
      "cropped_path": "user255_additional_3.jpg",
      "embedding_path": "user255_additional_3_embedding.npy",
      "face_detected": true,
      "face_info": {
        "bbox": "[ 36.725243 320.16034  191.23186  510.15033 ]",
        "det_score": "0.89600956",
        "age": 28,
        "gender": "1"
      }
    },
    {
      "original_url": "https://apps.parthaisolutions.com/ai-matchmaking/api/matrimony/static/profile_pics/1834414e-676d-42e7-abb2-63eaf64703cf/83fe2273-a79c-4f93-9028-f1c996dafa6a.jpg",
      "cropped_path": "user255_additional_4.jpg",
      "embedding_path": "user255_additional_4_embedding.npy",
      "face_detected": true,
      "face_info": {
        "bbox": "[170.60864 109.1122  285.00308 244.97798]",
        "det_score": "0.86734533",
        "age": 26,
        "gender": "1"
      }
    }
  ],
  "cropped_images": [
    "user255_primary.jpg",
    "user255_additional_1.jpg",
    "user255_additional_2.jpg",
    "user255_additional_3.jpg",
    "user255_additional_4.jpg"
  ]
}