{
  "user_id": "0b3345df-9904-40e1-bf85-dc971a9d67ca",
  "user_number": 106,
  "primary_photo": {
    "original_url": "https://apps.parthaisolutions.com/ai-matchmaking/api/matrimony/static/profile_pics/0b3345df-9904-40e1-bf85-dc971a9d67ca/981b6d23-b990-4067-8f4a-5505e7c8f2d0.jpg",
    "cropped_path": "user106_primary.jpg",
    "embedding_path": "user106_primary_embedding.npy",
    "face_detected": true,
    "face_info": {
      "bbox": "[195.69041 264.19058 410.46094 569.15173]",
      "det_score": "0.86686766",
      "age": 54,
      "gender": "1"
    }
  },
  "additional_photos": [
    {
      "original_url": "https://apps.parthaisolutions.com/ai-matchmaking/api/matrimony/static/profile_pics/0b3345df-9904-40e1-bf85-dc971a9d67ca/896f5f1a-0d39-4e49-9088-7da13d47728d.jpg",
      "cropped_path": "user106_additional_1.jpg",
      "embedding_path": "user106_additional_1_embedding.npy",
      "face_detected": true,
      "face_info": {
        "bbox": "[121.68711   74.566574 369.73672  427.74942 ]",
        "det_score": "0.7806426",
        "age": 66,
        "gender": "1"
      }
    },
    {
      "original_url": "https://apps.parthaisolutions.com/ai-matchmaking/api/matrimony/static/profile_pics/0b3345df-9904-40e1-bf85-dc971a9d67ca/a1491a62-df15-420f-af53-3a63404490b4.jpg",
      "cropped_path": "user106_additional_2.jpg",
      "embedding_path": "user106_additional_2_embedding.npy",
      "face_detected": true,
      "face_info": {
        "bbox": "[147.7268  258.96225 257.48892 411.51773]",
        "det_score": "0.90941817",
        "age": 34,
        "gender": "0"
      }
    },
    {
      "original_url": "https://apps.parthaisolutions.com/ai-matchmaking/api/matrimony/static/profile_pics/0b3345df-9904-40e1-bf85-dc971a9d67ca/b78aa4e5-0f99-4c2d-98a7-4d503986bb67.jpg",
      "cropped_path": "user106_additional_3.jpg",
      "embedding_path": "user106_additional_3_embedding.npy",
      "face_detected": true,
      "face_info": {
        "bbox": "[221.37851 102.69893 283.8472  182.73131]",
        "det_score": "0.8207706",
        "age": 43,
        "gender": "1"
      }
    }
  ],
  "cropped_images": [
    "user106_primary.jpg",
    "user106_additional_1.jpg",
    "user106_additional_2.jpg",
    "user106_additional_3.jpg"
  ]
}