{
  "user_id": "49073123-7b92-42b5-a462-16e3a1171b78",
  "user_number": 754,
  "primary_photo": {
    "original_url": "https://apps.parthaisolutions.com/ai-matchmaking/api/matrimony/static/profile_pics/49073123-7b92-42b5-a462-16e3a1171b78/8d1541b1-688b-4d96-872b-65a7b87c3dd6.jpg",
    "cropped_path": "user754_primary.jpg",
    "embedding_path": "user754_primary_embedding.npy",
    "face_detected": true,
    "face_info": {
      "bbox": "[237.88095 519.7916  467.1215  803.79846]",
      "det_score": "0.8694755",
      "age": 47,
      "gender": "1"
    }
  },
  "additional_photos": [
    {
      "original_url": "https://apps.parthaisolutions.com/ai-matchmaking/api/matrimony/static/profile_pics/49073123-7b92-42b5-a462-16e3a1171b78/1343f3a6-67f6-4774-b334-29380e07b8c7.jpg",
      "cropped_path": "user754_additional_1.jpg",
      "embedding_path": "user754_additional_1_embedding.npy",
      "face_detected": true,
      "face_info": {
        "bbox": "[210.2758  137.96812 324.6474  297.01236]",
        "det_score": "0.78172517",
        "age": 35,
        "gender": "0"
      }
    },
    {
      "original_url": "https://apps.parthaisolutions.com/ai-matchmaking/api/matrimony/static/profile_pics/49073123-7b92-42b5-a462-16e3a1171b78/21489596-d567-4653-8d4b-8801ae757801.jpg",
      "cropped_path": "user754_additional_2.jpg",
      "embedding_path": "user754_additional_2_embedding.npy",
      "face_detected": true,
      "face_info": {
        "bbox": "[495.07657 774.9967  572.5942  880.49695]",
        "det_score": "0.8329179",
        "age": 53,
        "gender": "1"
      }
    }
  ],
  "cropped_images": [
    "user754_primary.jpg",
    "user754_additional_1.jpg",
    "user754_additional_2.jpg"
  ]
}