{
  "user_id": "3359a9f3-11e6-4097-a110-d9d713fb0528",
  "user_number": 516,
  "primary_photo": {
    "original_url": "https://apps.parthaisolutions.com/ai-matchmaking/api/matrimony/static/profile_pics/3359a9f3-11e6-4097-a110-d9d713fb0528/4b7bd123-fa5b-48fa-93fb-53ab8b4c7625.jpg",
    "cropped_path": "user516_primary.jpg",
    "embedding_path": "user516_primary_embedding.npy",
    "face_detected": true,
    "face_info": {
      "bbox": "[559.30237 417.89883 760.57263 640.3167 ]",
      "det_score": "0.9028654",
      "age": 31,
      "gender": "1"
    }
  },
  "additional_photos": [
    {
      "original_url": "https://apps.parthaisolutions.com/ai-matchmaking/api/matrimony/static/profile_pics/3359a9f3-11e6-4097-a110-d9d713fb0528/a2ff5f78-2a14-4b50-8532-651cf3b48fec.jpg",
      "cropped_path": "user516_additional_1.jpg",
      "embedding_path": "user516_additional_1_embedding.npy",
      "face_detected": true,
      "face_info": {
        "bbox": "[512.58527 380.19165 559.3089  433.20377]",
        "det_score": "0.85196966",
        "age": 29,
        "gender": "1"
      }
    },
    {
      "original_url": "https://apps.parthaisolutions.com/ai-matchmaking/api/matrimony/static/profile_pics/3359a9f3-11e6-4097-a110-d9d713fb0528/70f82b40-89e3-4500-8dbf-dce0dcf62409.jpg",
      "cropped_path": "user516_additional_2.jpg",
      "embedding_path": "user516_additional_2_embedding.npy",
      "face_detected": true,
      "face_info": {
        "bbox": "[241.00723   33.118835 330.45172  144.1413  ]",
        "det_score": "0.87135184",
        "age": 33,
        "gender": "1"
      }
    },
    {
      "original_url": "https://apps.parthaisolutions.com/ai-matchmaking/api/matrimony/static/profile_pics/3359a9f3-11e6-4097-a110-d9d713fb0528/3da39035-ac2f-45d6-9f4c-f4f7f9ea1b3c.jpg",
      "cropped_path": "user516_additional_3.jpg",
      "embedding_path": "user516_additional_3_embedding.npy",
      "face_detected": true,
      "face_info": {
        "bbox": "[594.8848  325.61603 797.5381  573.20703]",
        "det_score": "0.90419114",
        "age": 22,
        "gender": "1"
      }
    },
    {
      "original_url": "https://apps.parthaisolutions.com/ai-matchmaking/api/matrimony/static/profile_pics/3359a9f3-11e6-4097-a110-d9d713fb0528/dc07aa8a-0c6a-4c7c-bc8d-9a82bfbae1b3.jpg",
      "cropped_path": "user516_additional_4.jpg",
      "embedding_path": "user516_additional_4_embedding.npy",
      "face_detected": true,
      "face_info": {
        "bbox": "[246.88269 361.6186  295.80145 419.37686]",
        "det_score": "0.8899767",
        "age": 36,
        "gender": "1"
      }
    }
  ],
  "cropped_images": [
    "user516_primary.jpg",
    "user516_additional_1.jpg",
    "user516_additional_2.jpg",
    "user516_additional_3.jpg",
    "user516_additional_4.jpg"
  ]
}