{
  "user_id": "5fe1b965-bf5f-4cbb-ad77-7aad73db3984",
  "user_number": 952,
  "primary_photo": {
    "original_url": "https://apps.parthaisolutions.com/ai-matchmaking/api/matrimony/static/profile_pics/5fe1b965-bf5f-4cbb-ad77-7aad73db3984/c6a5574c-28c4-411e-8c22-18a9c483514e.jpg",
    "cropped_path": "user952_primary.jpg",
    "embedding_path": "user952_primary_embedding.npy",
    "face_detected": true,
    "face_info": {
      "bbox": "[327.3847   36.93977 579.3294  377.96698]",
      "det_score": "0.7858418",
      "age": 44,
      "gender": "1"
    }
  },
  "additional_photos": [
    {
      "original_url": "https://apps.parthaisolutions.com/ai-matchmaking/api/matrimony/static/profile_pics/5fe1b965-bf5f-4cbb-ad77-7aad73db3984/ebe749f7-0f3f-4672-9cfb-402daf6eb4de.jpg",
      "cropped_path": "user952_additional_1.jpg",
      "embedding_path": "user952_additional_1_embedding.npy",
      "face_detected": true,
      "face_info": {
        "bbox": "[353.38507 297.8282  592.4051  608.0971 ]",
        "det_score": "0.8436469",
        "age": 37,
        "gender": "1"
      }
    },
    {
      "original_url": "https://apps.parthaisolutions.com/ai-matchmaking/api/matrimony/static/profile_pics/5fe1b965-bf5f-4cbb-ad77-7aad73db3984/5d216b22-26ba-43e0-b316-a0892df2333a.jpg",
      "cropped_path": "user952_additional_2.jpg",
      "embedding_path": "user952_additional_2_embedding.npy",
      "face_detected": true,
      "face_info": {
        "bbox": "[326.01376 257.51978 553.2804  560.6593 ]",
        "det_score": "0.8878025",
        "age": 56,
        "gender": "1"
      }
    },
    {
      "original_url": "https://apps.parthaisolutions.com/ai-matchmaking/api/matrimony/static/profile_pics/5fe1b965-bf5f-4cbb-ad77-7aad73db3984/64333658-8a77-458c-be84-3e8d3b1e95df.jpg",
      "cropped_path": "user952_additional_3.jpg",
      "embedding_path": "user952_additional_3_embedding.npy",
      "face_detected": true,
      "face_info": {
        "bbox": "[129.52975 301.80737 423.1162  647.8545 ]",
        "det_score": "0.82003796",
        "age": 48,
        "gender": "1"
      }
    },
    {
      "original_url": "https://apps.parthaisolutions.com/ai-matchmaking/api/matrimony/static/profile_pics/5fe1b965-bf5f-4cbb-ad77-7aad73db3984/110aaaf8-32df-46fd-b645-6df3accd95d1.jpg",
      "cropped_path": "user952_additional_4.jpg",
      "embedding_path": "user952_additional_4_embedding.npy",
      "face_detected": true,
      "face_info": {
        "bbox": "[254.71553  61.22589 342.8389  167.70926]",
        "det_score": "0.8295788",
        "age": 50,
        "gender": "1"
      }
    }
  ],
  "cropped_images": [
    "user952_primary.jpg",
    "user952_additional_1.jpg",
    "user952_additional_2.jpg",
    "user952_additional_3.jpg",
    "user952_additional_4.jpg"
  ]
}