{
  "user_id": "985c33dd-c613-4f9f-80b2-a82568e2eaa7",
  "user_number": 1494,
  "primary_photo": {
    "original_url": "https://apps.parthaisolutions.com/ai-matchmaking/api/matrimony/static/profile_pics/985c33dd-c613-4f9f-80b2-a82568e2eaa7/2d6b765c-534b-4427-88a3-2088bd78a018.jpg",
    "cropped_path": "user1494_primary.jpg",
    "embedding_path": "user1494_primary_embedding.npy",
    "face_detected": true,
    "face_info": {
      "bbox": "[132.92195 419.2396  378.02603 744.19696]",
      "det_score": "0.81747407",
      "age": 57,
      "gender": "1"
    }
  },
  "additional_photos": [
    {
      "original_url": "https://apps.parthaisolutions.com/ai-matchmaking/api/matrimony/static/profile_pics/985c33dd-c613-4f9f-80b2-a82568e2eaa7/fc2c9e89-bca5-495b-a270-83e83a8a0204.jpg",
      "cropped_path": "user1494_additional_1.jpg",
      "embedding_path": "user1494_additional_1_embedding.npy",
      "face_detected": true,
      "face_info": {
        "bbox": "[286.49146 428.49493 394.63934 574.87164]",
        "det_score": "0.7812239",
        "age": 39,
        "gender": "1"
      }
    },
    {
      "original_url": "https://apps.parthaisolutions.com/ai-matchmaking/api/matrimony/static/profile_pics/985c33dd-c613-4f9f-80b2-a82568e2eaa7/3e4feb2d-879c-4ea8-8657-be14aa3dcf76.jpg",
      "cropped_path": "user1494_additional_2.jpg",
      "embedding_path": "user1494_additional_2_embedding.npy",
      "face_detected": true,
      "face_info": {
        "bbox": "[537.95905 194.72124 729.0988  431.52954]",
        "det_score": "0.88732165",
        "age": 36,
        "gender": "1"
      }
    },
    {
      "original_url": "https://apps.parthaisolutions.com/ai-matchmaking/api/matrimony/static/profile_pics/985c33dd-c613-4f9f-80b2-a82568e2eaa7/126103d1-b8bc-4957-b783-296ee731aa8e.jpg",
      "cropped_path": "user1494_additional_3.jpg",
      "embedding_path": "user1494_additional_3_embedding.npy",
      "face_detected": true,
      "face_info": {
        "bbox": "[126.14596 452.03867 410.78067 810.4598 ]",
        "det_score": "0.7776374",
        "age": 40,
        "gender": "1"
      }
    },
    {
      "original_url": "https://apps.parthaisolutions.com/ai-matchmaking/api/matrimony/static/profile_pics/985c33dd-c613-4f9f-80b2-a82568e2eaa7/960fe495-3629-4e83-96e1-81897db4085c.jpg",
      "cropped_path": "user1494_additional_4.jpg",
      "embedding_path": "user1494_additional_4_embedding.npy",
      "face_detected": true,
      "face_info": {
        "bbox": "[108.56858 394.64603 348.52512 665.7723 ]",
        "det_score": "0.8621956",
        "age": 42,
        "gender": "1"
      }
    }
  ],
  "cropped_images": [
    "user1494_primary.jpg",
    "user1494_additional_1.jpg",
    "user1494_additional_2.jpg",
    "user1494_additional_3.jpg",
    "user1494_additional_4.jpg"
  ]
}